[{"timestamp":"2024-01-11T00:38:41.424Z","count":0,"uniques":0},{"timestamp":"2024-01-12T00:38:32.191Z","count":0,"uniques":0},{"timestamp":"2024-01-13T00:38:01.104Z","count":0,"uniques":0},{"timestamp":"2024-01-14T00:41:46.714Z","count":0,"uniques":0},{"timestamp":"2024-01-15T00:40:15.715Z","count":0,"uniques":0},{"timestamp":"2024-01-16T00:38:12.717Z","count":0,"uniques":0},{"timestamp":"2024-01-17T00:38:46.220Z","count":0,"uniques":0},{"timestamp":"2024-01-18T00:38:23.513Z","count":0,"uniques":0},{"timestamp":"2024-01-19T00:38:54.426Z","count":0,"uniques":0},{"timestamp":"2024-01-20T00:37:55.931Z","count":0,"uniques":0},{"timestamp":"2024-01-21T00:42:02.932Z","count":0,"uniques":0},{"timestamp":"2024-01-22T00:40:24.453Z","count":0,"uniques":0},{"timestamp":"2024-01-23T00:39:10.189Z","count":0,"uniques":0},{"timestamp":"2024-01-24T00:39:11.095Z","count":0,"uniques":0},{"timestamp":"2024-01-25T00:39:08.951Z","count":0,"uniques":0},{"timestamp":"2024-01-26T00:36:25.945Z","count":0,"uniques":0},{"timestamp":"2024-01-27T00:36:17.605Z","count":0,"uniques":0},{"timestamp":"2024-01-28T00:38:40.297Z","count":0,"uniques":0},{"timestamp":"2024-01-29T00:36:19.296Z","count":0,"uniques":0},{"timestamp":"2024-01-30T00:36:07.497Z","count":0,"uniques":0},{"timestamp":"2024-01-31T00:36:22.260Z","count":0,"uniques":0},{"timestamp":"2024-02-01T00:37:53.360Z","count":0,"uniques":0},{"timestamp":"2024-02-02T00:36:32.068Z","count":0,"uniques":0},{"timestamp":"2024-02-03T00:35:54.468Z","count":0,"uniques":0},{"timestamp":"2024-02-04T00:39:01.803Z","count":0,"uniques":0},{"timestamp":"2024-02-05T00:37:09.264Z","count":0,"uniques":0},{"timestamp":"2024-02-06T00:35:35.986Z","count":0,"uniques":0},{"timestamp":"2024-02-07T00:34:20.724Z","count":0,"uniques":0},{"timestamp":"2024-02-08T00:35:35.665Z","count":0,"uniques":0},{"timestamp":"2024-02-09T00:35:17.250Z","count":0,"uniques":0},{"timestamp":"2024-02-10T00:34:43.445Z","count":0,"uniques":0},{"timestamp":"2024-02-11T00:39:18.334Z","count":0,"uniques":0},{"timestamp":"2024-02-12T00:36:36.182Z","count":0,"uniques":0},{"timestamp":"2024-02-13T00:36:28.462Z","count":0,"uniques":0},{"timestamp":"2024-02-14T00:36:07.338Z","count":0,"uniques":0},{"timestamp":"2024-02-15T00:36:16.127Z","count":0,"uniques":0},{"timestamp":"2024-02-16T00:35:31.913Z","count":0,"uniques":0},{"timestamp":"2024-02-17T00:35:29.849Z","count":0,"uniques":0},{"timestamp":"2024-02-18T00:38:32.741Z","count":0,"uniques":0},{"timestamp":"2024-02-19T00:37:13.035Z","count":0,"uniques":0},{"timestamp":"2024-02-20T00:35:25.857Z","count":0,"uniques":0},{"timestamp":"2024-02-21T00:36:05.521Z","count":0,"uniques":0},{"timestamp":"2024-02-22T00:35:45.408Z","count":0,"uniques":0},{"timestamp":"2024-02-23T00:35:27.867Z","count":0,"uniques":0},{"timestamp":"2024-02-24T00:33:56.083Z","count":0,"uniques":0},{"timestamp":"2024-02-25T00:38:57.721Z","count":0,"uniques":0},{"timestamp":"2024-02-26T00:37:29.214Z","count":0,"uniques":0},{"timestamp":"2024-02-27T00:35:41.789Z","count":0,"uniques":0},{"timestamp":"2024-02-28T00:34:58.371Z","count":0,"uniques":0},{"timestamp":"2024-02-29T00:35:44.944Z","count":0,"uniques":0},{"timestamp":"2024-03-01T00:40:00.506Z","count":0,"uniques":0},{"timestamp":"2024-03-02T00:34:53.669Z","count":0,"uniques":0},{"timestamp":"2024-03-03T00:38:06.691Z","count":0,"uniques":0},{"timestamp":"2024-03-04T00:36:43.352Z","count":0,"uniques":0},{"timestamp":"2024-03-05T00:35:44.776Z","count":0,"uniques":0},{"timestamp":"2024-03-06T00:36:06.683Z","count":0,"uniques":0},{"timestamp":"2024-03-07T00:29:22.912Z","count":0,"uniques":0},{"timestamp":"2024-03-08T00:36:03.038Z","count":0,"uniques":0},{"timestamp":"2024-03-09T00:34:41.049Z","count":0,"uniques":0},{"timestamp":"2024-03-10T00:39:01.390Z","count":0,"uniques":0},{"timestamp":"2024-03-11T00:37:16.555Z","count":0,"uniques":0},{"timestamp":"2024-03-12T00:35:29.688Z","count":0,"uniques":0},{"timestamp":"2024-03-13T00:36:21.811Z","count":0,"uniques":0},{"timestamp":"2024-03-14T00:35:30.053Z","count":0,"uniques":0},{"timestamp":"2024-03-15T00:36:16.581Z","count":0,"uniques":0},{"timestamp":"2024-03-16T00:34:37.566Z","count":0,"uniques":0},{"timestamp":"2024-03-17T00:38:46.995Z","count":0,"uniques":0},{"timestamp":"2024-03-18T00:37:08.769Z","count":0,"uniques":0},{"timestamp":"2024-03-19T00:36:05.982Z","count":0,"uniques":0},{"timestamp":"2024-03-20T00:35:48.590Z","count":0,"uniques":0},{"timestamp":"2024-03-21T00:37:22.361Z","count":0,"uniques":0},{"timestamp":"2024-03-22T00:35:46.724Z","count":0,"uniques":0},{"timestamp":"2024-03-23T00:35:27.888Z","count":0,"uniques":0},{"timestamp":"2024-03-24T00:40:40.666Z","count":0,"uniques":0},{"timestamp":"2024-03-25T00:37:40.677Z","count":0,"uniques":0},{"timestamp":"2024-03-26T00:36:23.333Z","count":0,"uniques":0},{"timestamp":"2024-03-27T00:36:08.634Z","count":0,"uniques":0},{"timestamp":"2024-03-28T00:36:41.706Z","count":0,"uniques":0},{"timestamp":"2024-03-29T00:36:16.390Z","count":0,"uniques":0},{"timestamp":"2024-03-30T00:35:10.979Z","count":0,"uniques":0},{"timestamp":"2024-03-31T00:40:29.977Z","count":0,"uniques":0},{"timestamp":"2024-04-01T00:40:32.565Z","count":0,"uniques":0},{"timestamp":"2024-04-02T00:37:18.314Z","count":0,"uniques":0},{"timestamp":"2024-04-03T00:36:08.454Z","count":0,"uniques":0},{"timestamp":"2024-04-04T00:37:55.069Z","count":0,"uniques":0},{"timestamp":"2024-04-05T00:37:04.511Z","count":0,"uniques":0},{"timestamp":"2024-04-06T00:36:10.602Z","count":0,"uniques":0},{"timestamp":"2024-04-07T00:40:42.172Z","count":0,"uniques":0},{"timestamp":"2024-04-08T00:38:00.240Z","count":0,"uniques":0},{"timestamp":"2024-04-09T00:36:59.769Z","count":0,"uniques":0},{"timestamp":"2024-04-10T00:36:41.386Z","count":0,"uniques":0},{"timestamp":"2024-04-11T00:37:11.108Z","count":0,"uniques":0},{"timestamp":"2024-04-12T00:37:20.205Z","count":0,"uniques":0},{"timestamp":"2024-04-13T00:31:27.531Z","count":0,"uniques":0},{"timestamp":"2024-04-14T00:42:22.096Z","count":0,"uniques":0},{"timestamp":"2024-04-15T03:05:58.624Z","count":0,"uniques":0},{"timestamp":"2024-04-16T00:36:38.023Z","count":0,"uniques":0},{"timestamp":"2024-04-17T00:37:16.802Z","count":0,"uniques":0},{"timestamp":"2024-04-18T00:36:45.071Z","count":0,"uniques":0},{"timestamp":"2024-04-19T00:37:05.499Z","count":0,"uniques":0},{"timestamp":"2024-04-20T00:37:00.260Z","count":0,"uniques":0},{"timestamp":"2024-04-21T00:40:17.128Z","count":0,"uniques":0},{"timestamp":"2024-04-22T00:38:38.642Z","count":0,"uniques":0},{"timestamp":"2024-04-23T00:37:23.344Z","count":0,"uniques":0},{"timestamp":"2024-04-24T00:39:33.820Z","count":0,"uniques":0},{"timestamp":"2024-04-25T00:39:45.138Z","count":0,"uniques":0},{"timestamp":"2024-04-26T00:37:24.679Z","count":0,"uniques":0},{"timestamp":"2024-04-27T00:37:15.230Z","count":0,"uniques":0},{"timestamp":"2024-04-28T00:41:06.412Z","count":0,"uniques":0},{"timestamp":"2024-04-29T00:38:18.429Z","count":0,"uniques":0},{"timestamp":"2024-04-30T00:36:35.027Z","count":0,"uniques":0},{"timestamp":"2024-05-01T00:40:39.221Z","count":0,"uniques":0},{"timestamp":"2024-05-02T00:37:07.362Z","count":0,"uniques":0},{"timestamp":"2024-05-03T00:40:04.830Z","count":0,"uniques":0},{"timestamp":"2024-05-04T00:37:10.341Z","count":0,"uniques":0},{"timestamp":"2024-05-05T00:40:32.437Z","count":0,"uniques":0},{"timestamp":"2024-05-06T00:38:38.880Z","count":0,"uniques":0},{"timestamp":"2024-05-07T00:37:59.467Z","count":0,"uniques":0},{"timestamp":"2024-05-08T00:31:38.042Z","count":0,"uniques":0},{"timestamp":"2024-05-09T00:38:08.080Z","count":0,"uniques":0},{"timestamp":"2024-05-10T00:37:58.409Z","count":0,"uniques":0},{"timestamp":"2024-05-11T00:37:29.789Z","count":0,"uniques":0},{"timestamp":"2024-05-12T00:42:01.104Z","count":0,"uniques":0},{"timestamp":"2024-05-13T00:39:49.602Z","count":0,"uniques":0},{"timestamp":"2024-05-14T00:38:19.256Z","count":0,"uniques":0},{"timestamp":"2024-05-15T00:38:28.772Z","count":0,"uniques":0},{"timestamp":"2024-05-16T00:38:02.855Z","count":0,"uniques":0},{"timestamp":"2024-05-17T00:38:39.896Z","count":0,"uniques":0},{"timestamp":"2024-05-18T00:38:16.114Z","count":0,"uniques":0},{"timestamp":"2024-05-19T00:41:47.618Z","count":0,"uniques":0},{"timestamp":"2024-05-20T00:39:31.777Z","count":0,"uniques":0},{"timestamp":"2024-05-21T00:39:03.558Z","count":0,"uniques":0},{"timestamp":"2024-05-22T00:38:48.721Z","count":0,"uniques":0},{"timestamp":"2024-05-23T00:38:43.063Z","count":0,"uniques":0},{"timestamp":"2024-05-24T00:39:02.836Z","count":0,"uniques":0},{"timestamp":"2024-05-25T00:37:57.613Z","count":0,"uniques":0},{"timestamp":"2024-05-26T00:42:09.625Z","count":0,"uniques":0},{"timestamp":"2024-05-27T00:39:57.430Z","count":0,"uniques":0},{"timestamp":"2024-05-28T00:39:06.668Z","count":0,"uniques":0},{"timestamp":"2024-05-29T00:42:22.345Z","count":0,"uniques":0},{"timestamp":"2024-05-30T00:39:41.516Z","count":0,"uniques":0},{"timestamp":"2024-05-31T00:39:57.637Z","count":0,"uniques":0},{"timestamp":"2024-06-01T00:42:15.771Z","count":0,"uniques":0},{"timestamp":"2024-06-02T00:42:49.379Z","count":0,"uniques":0},{"timestamp":"2024-06-03T00:40:39.063Z","count":0,"uniques":0},{"timestamp":"2024-06-04T06:12:25.517Z","count":0,"uniques":0},{"timestamp":"2024-06-05T00:39:22.926Z","count":0,"uniques":0},{"timestamp":"2024-06-06T00:39:29.235Z","count":0,"uniques":0},{"timestamp":"2024-06-07T00:40:42.088Z","count":0,"uniques":0},{"timestamp":"2024-06-08T00:40:05.910Z","count":0,"uniques":0},{"timestamp":"2024-06-09T00:44:18.965Z","count":0,"uniques":0},{"timestamp":"2024-06-10T00:41:36.898Z","count":0,"uniques":0},{"timestamp":"2024-06-11T00:40:19.657Z","count":0,"uniques":0},{"timestamp":"2024-06-12T00:40:20.099Z","count":0,"uniques":0},{"timestamp":"2024-06-13T00:39:58.675Z","count":0,"uniques":0},{"timestamp":"2024-06-14T00:39:48.555Z","count":0,"uniques":0},{"timestamp":"2024-06-15T00:39:48.926Z","count":0,"uniques":0},{"timestamp":"2024-06-16T00:43:52.434Z","count":0,"uniques":0},{"timestamp":"2024-06-17T00:42:11.955Z","count":0,"uniques":0},{"timestamp":"2024-06-18T00:40:55.330Z","count":0,"uniques":0},{"timestamp":"2024-06-19T00:40:33.232Z","count":0,"uniques":0},{"timestamp":"2024-06-20T00:39:30.028Z","count":0,"uniques":0},{"timestamp":"2024-06-21T00:39:39.173Z","count":0,"uniques":0},{"timestamp":"2024-06-22T00:39:30.348Z","count":0,"uniques":0},{"timestamp":"2024-06-23T00:43:22.253Z","count":0,"uniques":0},{"timestamp":"2024-06-24T00:41:56.887Z","count":0,"uniques":0},{"timestamp":"2024-06-25T00:40:11.217Z","count":0,"uniques":0},{"timestamp":"2024-06-26T00:40:17.073Z","count":0,"uniques":0},{"timestamp":"2024-06-27T00:40:39.788Z","count":0,"uniques":0},{"timestamp":"2024-06-28T00:40:56.447Z","count":0,"uniques":0},{"timestamp":"2024-06-29T00:39:47.809Z","count":0,"uniques":0},{"timestamp":"2024-06-30T00:44:33.221Z","count":0,"uniques":0},{"timestamp":"2024-07-01T00:46:27.272Z","count":0,"uniques":0},{"timestamp":"2024-07-02T00:40:57.053Z","count":0,"uniques":0},{"timestamp":"2024-07-03T00:40:39.038Z","count":0,"uniques":0},{"timestamp":"2024-07-04T00:41:02.555Z","count":0,"uniques":0},{"timestamp":"2024-07-05T00:40:39.178Z","count":0,"uniques":0},{"timestamp":"2024-07-06T00:39:40.175Z","count":0,"uniques":0},{"timestamp":"2024-07-07T00:44:56.050Z","count":0,"uniques":0},{"timestamp":"2024-07-08T00:42:30.627Z","count":0,"uniques":0},{"timestamp":"2024-07-09T00:41:23.202Z","count":0,"uniques":0},{"timestamp":"2024-07-10T00:41:49.139Z","count":0,"uniques":0},{"timestamp":"2024-07-11T00:42:13.438Z","count":0,"uniques":0},{"timestamp":"2024-07-12T00:41:08.642Z","count":0,"uniques":0},{"timestamp":"2024-07-13T00:41:43.332Z","count":0,"uniques":0},{"timestamp":"2024-07-14T00:45:46.377Z","count":0,"uniques":0},{"timestamp":"2024-07-15T00:43:18.426Z","count":0,"uniques":0},{"timestamp":"2024-07-16T00:42:01.615Z","count":0,"uniques":0},{"timestamp":"2024-07-17T00:42:09.639Z","count":0,"uniques":0},{"timestamp":"2024-07-18T00:41:24.478Z","count":0,"uniques":0},{"timestamp":"2024-07-19T00:41:58.323Z","count":0,"uniques":0},{"timestamp":"2024-07-20T00:41:04.446Z","count":0,"uniques":0},{"timestamp":"2024-07-21T00:45:38.183Z","count":0,"uniques":0},{"timestamp":"2024-07-22T00:43:40.440Z","count":0,"uniques":0},{"timestamp":"2024-07-23T00:42:17.795Z","count":0,"uniques":0},{"timestamp":"2024-07-24T00:43:00.991Z","count":0,"uniques":0},{"timestamp":"2024-07-25T00:41:59.486Z","count":0,"uniques":0},{"timestamp":"2024-07-26T00:41:45.602Z","count":0,"uniques":0},{"timestamp":"2024-07-27T00:41:34.852Z","count":0,"uniques":0},{"timestamp":"2024-07-28T00:46:14.396Z","count":0,"uniques":0},{"timestamp":"2024-07-29T00:43:39.291Z","count":0,"uniques":0},{"timestamp":"2024-07-30T00:42:19.408Z","count":0,"uniques":0},{"timestamp":"2024-07-31T00:35:07.498Z","count":0,"uniques":0},{"timestamp":"2024-08-01T00:46:46.252Z","count":0,"uniques":0},{"timestamp":"2024-08-02T00:42:09.359Z","count":0,"uniques":0},{"timestamp":"2024-08-03T00:41:28.631Z","count":0,"uniques":0},{"timestamp":"2024-08-04T00:46:18.084Z","count":0,"uniques":0},{"timestamp":"2024-08-05T00:44:10.588Z","count":0,"uniques":0},{"timestamp":"2024-08-06T00:42:27.541Z","count":0,"uniques":0},{"timestamp":"2024-08-07T00:42:59.760Z","count":0,"uniques":0},{"timestamp":"2024-08-08T00:42:30.909Z","count":0,"uniques":0},{"timestamp":"2024-08-09T00:43:23.077Z","count":0,"uniques":0},{"timestamp":"2024-08-10T00:42:46.293Z","count":0,"uniques":0},{"timestamp":"2024-08-11T00:47:07.742Z","count":0,"uniques":0},{"timestamp":"2024-08-12T00:44:23.705Z","count":0,"uniques":0},{"timestamp":"2024-08-13T00:43:49.411Z","count":0,"uniques":0},{"timestamp":"2024-08-14T00:43:02.519Z","count":0,"uniques":0},{"timestamp":"2024-08-15T00:41:21.240Z","count":0,"uniques":0},{"timestamp":"2024-08-16T00:42:28.983Z","count":0,"uniques":0},{"timestamp":"2024-08-17T00:41:28.407Z","count":0,"uniques":0},{"timestamp":"2024-08-18T00:46:13.799Z","count":0,"uniques":0},{"timestamp":"2024-08-19T00:43:44.624Z","count":0,"uniques":0},{"timestamp":"2024-08-20T00:42:44.617Z","count":0,"uniques":0},{"timestamp":"2024-08-21T00:42:47.364Z","count":0,"uniques":0},{"timestamp":"2024-08-22T00:43:43.844Z","count":0,"uniques":0},{"timestamp":"2024-08-23T00:42:55.120Z","count":0,"uniques":0},{"timestamp":"2024-08-24T00:41:59.897Z","count":0,"uniques":0},{"timestamp":"2024-08-25T00:47:33.038Z","count":0,"uniques":0},{"timestamp":"2024-08-26T00:43:47.212Z","count":0,"uniques":0},{"timestamp":"2024-08-27T00:43:54.008Z","count":0,"uniques":0},{"timestamp":"2024-08-28T00:43:59.628Z","count":0,"uniques":0},{"timestamp":"2024-08-29T00:44:23.324Z","count":0,"uniques":0},{"timestamp":"2024-08-30T00:44:41.718Z","count":0,"uniques":0},{"timestamp":"2024-08-31T00:44:48.169Z","count":0,"uniques":0},{"timestamp":"2024-09-01T00:53:59.491Z","count":0,"uniques":0},{"timestamp":"2024-09-02T00:46:18.162Z","count":0,"uniques":0},{"timestamp":"2024-09-03T00:44:17.561Z","count":0,"uniques":0},{"timestamp":"2024-09-04T00:44:59.486Z","count":0,"uniques":0},{"timestamp":"2024-09-05T00:44:59.465Z","count":0,"uniques":0},{"timestamp":"2024-09-06T00:45:03.974Z","count":0,"uniques":0},{"timestamp":"2024-09-07T00:44:10.309Z","count":0,"uniques":0},{"timestamp":"2024-09-08T00:50:28.361Z","count":0,"uniques":0},{"timestamp":"2024-09-09T00:47:41.397Z","count":0,"uniques":0},{"timestamp":"2024-09-10T00:45:26.938Z","count":0,"uniques":0},{"timestamp":"2024-09-11T00:44:58.356Z","count":0,"uniques":0},{"timestamp":"2024-09-12T00:45:23.225Z","count":0,"uniques":0},{"timestamp":"2024-09-13T00:45:27.267Z","count":0,"uniques":0},{"timestamp":"2024-09-14T00:44:53.725Z","count":0,"uniques":0},{"timestamp":"2024-09-15T00:52:19.917Z","count":0,"uniques":0},{"timestamp":"2024-09-16T00:49:38.366Z","count":0,"uniques":0},{"timestamp":"2024-09-17T00:38:15.168Z","count":0,"uniques":0},{"timestamp":"2024-09-18T00:45:21.041Z","count":0,"uniques":0},{"timestamp":"2024-09-19T00:46:22.603Z","count":0,"uniques":0},{"timestamp":"2024-09-20T00:46:24.345Z","count":0,"uniques":0},{"timestamp":"2024-09-21T00:45:18.726Z","count":0,"uniques":0},{"timestamp":"2024-09-22T00:52:27.440Z","count":0,"uniques":0},{"timestamp":"2024-09-23T00:48:43.303Z","count":0,"uniques":0},{"timestamp":"2024-09-24T00:48:17.252Z","count":0,"uniques":0},{"timestamp":"2024-09-25T00:49:03.373Z","count":0,"uniques":0},{"timestamp":"2024-09-26T00:47:45.964Z","count":0,"uniques":0},{"timestamp":"2024-09-27T00:48:06.380Z","count":0,"uniques":0},{"timestamp":"2024-09-28T00:47:32.917Z","count":0,"uniques":0},{"timestamp":"2024-09-29T00:53:23.659Z","count":0,"uniques":0},{"timestamp":"2024-09-30T00:51:07.872Z","count":0,"uniques":0},{"timestamp":"2024-10-01T00:54:04.435Z","count":0,"uniques":0},{"timestamp":"2024-10-02T00:48:13.063Z","count":0,"uniques":0},{"timestamp":"2024-10-03T00:48:13.094Z","count":0,"uniques":0},{"timestamp":"2024-10-04T00:48:21.398Z","count":0,"uniques":0},{"timestamp":"2024-10-05T00:47:32.256Z","count":0,"uniques":0},{"timestamp":"2024-10-06T00:00:00.000Z","count":1,"uniques":1},{"timestamp":"2024-10-07T00:50:54.051Z","count":0,"uniques":0},{"timestamp":"2024-10-08T00:48:02.377Z","count":0,"uniques":0},{"timestamp":"2024-10-09T00:47:54.276Z","count":0,"uniques":0},{"timestamp":"2024-10-10T00:47:54.881Z","count":0,"uniques":0},{"timestamp":"2024-10-11T00:48:00.978Z","count":0,"uniques":0},{"timestamp":"2024-10-12T00:46:57.178Z","count":0,"uniques":0},{"timestamp":"2024-10-13T00:52:43.150Z","count":0,"uniques":0},{"timestamp":"2024-10-14T00:50:46.864Z","count":0,"uniques":0},{"timestamp":"2024-10-15T00:49:20.228Z","count":0,"uniques":0},{"timestamp":"2024-10-16T00:49:01.884Z","count":0,"uniques":0},{"timestamp":"2024-10-17T00:48:28.252Z","count":0,"uniques":0},{"timestamp":"2024-10-18T00:48:47.983Z","count":0,"uniques":0},{"timestamp":"2024-10-19T00:47:58.721Z","count":0,"uniques":0},{"timestamp":"2024-10-20T00:53:44.388Z","count":0,"uniques":0},{"timestamp":"2024-10-21T00:51:16.736Z","count":0,"uniques":0},{"timestamp":"2024-10-22T00:49:53.211Z","count":0,"uniques":0},{"timestamp":"2024-10-23T00:48:19.629Z","count":0,"uniques":0},{"timestamp":"2024-10-24T00:48:33.239Z","count":0,"uniques":0},{"timestamp":"2024-10-25T00:49:40.676Z","count":0,"uniques":0},{"timestamp":"2024-10-26T00:47:22.419Z","count":0,"uniques":0},{"timestamp":"2024-10-27T00:53:24.126Z","count":0,"uniques":0},{"timestamp":"2024-10-28T00:52:11.726Z","count":0,"uniques":0},{"timestamp":"2024-10-29T00:50:54.981Z","count":0,"uniques":0},{"timestamp":"2024-10-30T00:49:55.868Z","count":0,"uniques":0},{"timestamp":"2024-10-31T00:50:19.570Z","count":0,"uniques":0},{"timestamp":"2024-11-01T00:54:10.556Z","count":0,"uniques":0},{"timestamp":"2024-11-02T00:48:07.758Z","count":0,"uniques":0},{"timestamp":"2024-11-03T00:53:34.361Z","count":0,"uniques":0},{"timestamp":"2024-11-04T00:51:36.956Z","count":0,"uniques":0},{"timestamp":"2024-11-05T00:47:44.114Z","count":0,"uniques":0},{"timestamp":"2024-11-06T00:47:56.190Z","count":0,"uniques":0},{"timestamp":"2024-11-07T00:48:02.693Z","count":0,"uniques":0},{"timestamp":"2024-11-08T00:47:42.926Z","count":0,"uniques":0},{"timestamp":"2024-11-09T00:46:15.298Z","count":0,"uniques":0},{"timestamp":"2024-11-10T00:51:58.573Z","count":0,"uniques":0},{"timestamp":"2024-11-11T00:49:59.232Z","count":0,"uniques":0},{"timestamp":"2024-11-12T00:47:20.323Z","count":0,"uniques":0},{"timestamp":"2024-11-13T00:48:35.835Z","count":0,"uniques":0},{"timestamp":"2024-11-14T00:48:37.063Z","count":0,"uniques":0},{"timestamp":"2024-11-15T00:52:34.213Z","count":0,"uniques":0},{"timestamp":"2024-11-16T00:51:07.845Z","count":0,"uniques":0},{"timestamp":"2024-11-17T00:55:06.488Z","count":0,"uniques":0},{"timestamp":"2024-11-18T00:53:43.663Z","count":0,"uniques":0},{"timestamp":"2024-11-19T00:52:07.774Z","count":0,"uniques":0},{"timestamp":"2024-11-20T00:51:41.286Z","count":0,"uniques":0},{"timestamp":"2024-11-21T00:51:47.620Z","count":0,"uniques":0},{"timestamp":"2024-11-22T00:52:28.432Z","count":0,"uniques":0},{"timestamp":"2024-11-23T00:50:58.761Z","count":0,"uniques":0},{"timestamp":"2024-11-24T00:56:27.977Z","count":0,"uniques":0},{"timestamp":"2024-11-25T00:53:31.639Z","count":0,"uniques":0},{"timestamp":"2024-11-26T00:52:38.998Z","count":0,"uniques":0},{"timestamp":"2024-11-27T00:53:17.038Z","count":0,"uniques":0},{"timestamp":"2024-11-28T00:53:03.765Z","count":0,"uniques":0},{"timestamp":"2024-11-29T00:53:06.533Z","count":0,"uniques":0},{"timestamp":"2024-11-30T00:51:37.274Z","count":0,"uniques":0},{"timestamp":"2024-12-01T01:02:19.121Z","count":0,"uniques":0},{"timestamp":"2024-12-02T00:55:29.007Z","count":0,"uniques":0},{"timestamp":"2024-12-03T00:54:33.248Z","count":0,"uniques":0},{"timestamp":"2024-12-04T00:54:38.339Z","count":0,"uniques":0},{"timestamp":"2024-12-05T00:54:19.048Z","count":0,"uniques":0},{"timestamp":"2024-12-06T00:53:52.501Z","count":0,"uniques":0},{"timestamp":"2024-12-07T00:53:14.680Z","count":0,"uniques":0},{"timestamp":"2024-12-08T00:58:14.937Z","count":0,"uniques":0},{"timestamp":"2024-12-09T00:55:53.526Z","count":0,"uniques":0},{"timestamp":"2024-12-10T00:55:17.080Z","count":0,"uniques":0},{"timestamp":"2024-12-11T00:54:17.905Z","count":0,"uniques":0},{"timestamp":"2024-12-12T00:53:46.457Z","count":0,"uniques":0},{"timestamp":"2024-12-13T00:54:59.256Z","count":0,"uniques":0},{"timestamp":"2024-12-14T00:52:46.080Z","count":0,"uniques":0},{"timestamp":"2024-12-15T00:58:30.124Z","count":0,"uniques":0},{"timestamp":"2024-12-16T00:56:23.639Z","count":0,"uniques":0},{"timestamp":"2024-12-17T00:54:18.597Z","count":0,"uniques":0},{"timestamp":"2024-12-18T00:52:04.038Z","count":0,"uniques":0},{"timestamp":"2024-12-19T00:52:45.628Z","count":0,"uniques":0},{"timestamp":"2024-12-20T00:49:42.615Z","count":0,"uniques":0},{"timestamp":"2024-12-21T00:48:13.614Z","count":0,"uniques":0},{"timestamp":"2024-12-22T00:54:10.035Z","count":0,"uniques":0},{"timestamp":"2024-12-23T00:51:25.588Z","count":0,"uniques":0},{"timestamp":"2024-12-24T00:49:31.635Z","count":0,"uniques":0},{"timestamp":"2024-12-25T00:48:24.992Z","count":0,"uniques":0},{"timestamp":"2024-12-26T00:48:38.864Z","count":0,"uniques":0},{"timestamp":"2024-12-27T00:49:10.678Z","count":0,"uniques":0},{"timestamp":"2024-12-28T00:47:51.956Z","count":0,"uniques":0},{"timestamp":"2024-12-29T00:54:38.698Z","count":0,"uniques":0},{"timestamp":"2024-12-30T00:51:40.861Z","count":0,"uniques":0},{"timestamp":"2024-12-31T00:48:49.802Z","count":0,"uniques":0},{"timestamp":"2025-01-01T00:54:35.981Z","count":0,"uniques":0},{"timestamp":"2025-01-02T00:48:48.878Z","count":0,"uniques":0},{"timestamp":"2025-01-03T00:49:29.518Z","count":0,"uniques":0},{"timestamp":"2025-01-04T00:47:51.917Z","count":0,"uniques":0},{"timestamp":"2025-01-05T00:54:22.251Z","count":0,"uniques":0},{"timestamp":"2025-01-06T00:00:00.000Z","count":1,"uniques":1},{"timestamp":"2025-01-07T00:50:20.187Z","count":0,"uniques":0},{"timestamp":"2025-01-08T00:50:09.726Z","count":0,"uniques":0},{"timestamp":"2025-01-09T00:49:46.626Z","count":0,"uniques":0},{"timestamp":"2025-01-10T00:51:29.623Z","count":0,"uniques":0}]
