[{"timestamp":"2023-03-15T00:42:18.402Z","count":0,"uniques":0},{"timestamp":"2023-03-16T00:44:29.151Z","count":0,"uniques":0},{"timestamp":"2023-03-17T00:42:18.246Z","count":0,"uniques":0},{"timestamp":"2023-03-18T00:41:13.308Z","count":0,"uniques":0},{"timestamp":"2023-03-19T00:45:38.500Z","count":0,"uniques":0},{"timestamp":"2023-03-20T00:44:52.850Z","count":0,"uniques":0},{"timestamp":"2023-03-21T00:39:36.198Z","count":0,"uniques":0},{"timestamp":"2023-03-22T00:39:01.978Z","count":0,"uniques":0},{"timestamp":"2023-03-23T00:40:44.764Z","count":0,"uniques":0},{"timestamp":"2023-03-24T00:40:10.550Z","count":0,"uniques":0},{"timestamp":"2023-03-25T00:39:41.642Z","count":0,"uniques":0},{"timestamp":"2023-03-26T00:43:13.634Z","count":0,"uniques":0},{"timestamp":"2023-03-27T00:39:35.555Z","count":0,"uniques":0},{"timestamp":"2023-03-28T00:41:00.402Z","count":0,"uniques":0},{"timestamp":"2023-03-29T00:45:04.842Z","count":0,"uniques":0},{"timestamp":"2023-03-30T00:41:23.982Z","count":0,"uniques":0},{"timestamp":"2023-03-31T00:41:33.241Z","count":0,"uniques":0},{"timestamp":"2023-04-01T00:41:04.704Z","count":0,"uniques":0},{"timestamp":"2023-04-02T00:41:55.949Z","count":0,"uniques":0},{"timestamp":"2023-04-03T00:39:16.792Z","count":0,"uniques":0},{"timestamp":"2023-04-04T00:38:46.842Z","count":0,"uniques":0},{"timestamp":"2023-04-05T00:33:37.534Z","count":0,"uniques":0},{"timestamp":"2023-04-06T00:37:38.085Z","count":0,"uniques":0},{"timestamp":"2023-04-07T00:34:57.891Z","count":0,"uniques":0},{"timestamp":"2023-04-08T00:36:47.772Z","count":0,"uniques":0},{"timestamp":"2023-04-09T00:39:56.859Z","count":0,"uniques":0},{"timestamp":"2023-04-10T00:39:17.479Z","count":0,"uniques":0},{"timestamp":"2023-04-11T00:39:34.219Z","count":0,"uniques":0},{"timestamp":"2023-04-12T00:38:16.003Z","count":0,"uniques":0},{"timestamp":"2023-04-13T00:37:26.720Z","count":0,"uniques":0},{"timestamp":"2023-04-14T00:37:54.515Z","count":0,"uniques":0},{"timestamp":"2023-04-15T00:40:56.473Z","count":0,"uniques":0},{"timestamp":"2023-04-16T00:40:11.247Z","count":0,"uniques":0},{"timestamp":"2023-04-17T00:39:40.667Z","count":0,"uniques":0},{"timestamp":"2023-04-18T00:37:48.444Z","count":0,"uniques":0},{"timestamp":"2023-04-19T00:40:02.390Z","count":0,"uniques":0},{"timestamp":"2023-04-20T00:37:46.971Z","count":0,"uniques":0},{"timestamp":"2023-04-21T00:38:17.455Z","count":0,"uniques":0},{"timestamp":"2023-04-22T00:38:47.555Z","count":0,"uniques":0},{"timestamp":"2023-04-23T00:42:28.597Z","count":0,"uniques":0},{"timestamp":"2023-04-24T00:39:36.499Z","count":0,"uniques":0},{"timestamp":"2023-04-25T00:39:30.862Z","count":0,"uniques":0},{"timestamp":"2023-04-26T00:39:27.004Z","count":0,"uniques":0},{"timestamp":"2023-04-27T00:41:45.829Z","count":0,"uniques":0},{"timestamp":"2023-04-28T00:40:05.204Z","count":0,"uniques":0},{"timestamp":"2023-04-29T00:38:27.076Z","count":0,"uniques":0},{"timestamp":"2023-04-30T00:42:19.611Z","count":0,"uniques":0},{"timestamp":"2023-05-01T00:40:39.476Z","count":0,"uniques":0},{"timestamp":"2023-05-02T00:39:20.574Z","count":0,"uniques":0},{"timestamp":"2023-05-03T00:39:09.274Z","count":0,"uniques":0},{"timestamp":"2023-05-04T00:40:34.952Z","count":0,"uniques":0},{"timestamp":"2023-05-05T00:36:25.346Z","count":0,"uniques":0},{"timestamp":"2023-05-06T00:36:07.341Z","count":0,"uniques":0},{"timestamp":"2023-05-07T00:41:01.702Z","count":0,"uniques":0},{"timestamp":"2023-05-08T00:38:12.189Z","count":0,"uniques":0},{"timestamp":"2023-05-09T00:39:57.281Z","count":0,"uniques":0},{"timestamp":"2023-05-10T00:38:42.010Z","count":0,"uniques":0},{"timestamp":"2023-05-11T00:38:47.780Z","count":0,"uniques":0},{"timestamp":"2023-05-12T00:39:21.390Z","count":0,"uniques":0},{"timestamp":"2023-05-13T00:37:27.814Z","count":0,"uniques":0},{"timestamp":"2023-05-14T00:41:12.386Z","count":0,"uniques":0},{"timestamp":"2023-05-15T00:40:02.683Z","count":0,"uniques":0},{"timestamp":"2023-05-16T00:39:51.618Z","count":0,"uniques":0},{"timestamp":"2023-05-17T00:42:22.014Z","count":0,"uniques":0},{"timestamp":"2023-05-18T00:39:11.149Z","count":0,"uniques":0},{"timestamp":"2023-05-19T00:41:10.415Z","count":0,"uniques":0},{"timestamp":"2023-05-20T00:37:44.698Z","count":0,"uniques":0},{"timestamp":"2023-05-21T00:42:40.717Z","count":0,"uniques":0},{"timestamp":"2023-05-22T00:41:26.286Z","count":0,"uniques":0},{"timestamp":"2023-05-23T00:40:31.517Z","count":0,"uniques":0},{"timestamp":"2023-05-24T00:40:18.400Z","count":0,"uniques":0},{"timestamp":"2023-05-25T00:38:48.003Z","count":0,"uniques":0},{"timestamp":"2023-05-26T00:40:08.290Z","count":0,"uniques":0},{"timestamp":"2023-05-27T00:41:31.997Z","count":0,"uniques":0},{"timestamp":"2023-05-28T00:43:24.415Z","count":0,"uniques":0},{"timestamp":"2023-05-29T00:41:48.983Z","count":0,"uniques":0},{"timestamp":"2023-05-30T00:41:53.667Z","count":0,"uniques":0},{"timestamp":"2023-05-31T00:44:48.315Z","count":0,"uniques":0},{"timestamp":"2023-06-01T00:55:05.450Z","count":0,"uniques":0},{"timestamp":"2023-06-02T00:44:54.251Z","count":0,"uniques":0},{"timestamp":"2023-06-03T00:43:54.222Z","count":0,"uniques":0},{"timestamp":"2023-06-04T00:53:27.790Z","count":0,"uniques":0},{"timestamp":"2023-06-05T00:46:08.772Z","count":0,"uniques":0},{"timestamp":"2023-06-06T00:46:19.295Z","count":0,"uniques":0},{"timestamp":"2023-06-07T00:48:25.607Z","count":0,"uniques":0},{"timestamp":"2023-06-08T00:47:20.336Z","count":0,"uniques":0},{"timestamp":"2023-06-09T00:47:54.516Z","count":0,"uniques":0},{"timestamp":"2023-06-10T00:43:01.699Z","count":0,"uniques":0},{"timestamp":"2023-06-11T00:50:15.760Z","count":0,"uniques":0},{"timestamp":"2023-06-12T00:47:22.711Z","count":0,"uniques":0},{"timestamp":"2023-06-13T00:44:45.340Z","count":0,"uniques":0},{"timestamp":"2023-06-14T00:43:16.214Z","count":0,"uniques":0},{"timestamp":"2023-06-15T00:44:22.160Z","count":0,"uniques":0},{"timestamp":"2023-06-16T00:45:26.863Z","count":0,"uniques":0},{"timestamp":"2023-06-17T00:41:55.518Z","count":0,"uniques":0},{"timestamp":"2023-06-18T00:50:17.039Z","count":0,"uniques":0},{"timestamp":"2023-06-19T00:44:21.395Z","count":0,"uniques":0},{"timestamp":"2023-06-20T00:42:41.661Z","count":0,"uniques":0},{"timestamp":"2023-06-21T00:44:39.150Z","count":0,"uniques":0},{"timestamp":"2023-06-22T00:44:29.370Z","count":0,"uniques":0},{"timestamp":"2023-06-23T00:49:50.827Z","count":0,"uniques":0},{"timestamp":"2023-06-24T00:50:01.790Z","count":0,"uniques":0},{"timestamp":"2023-06-25T00:54:59.991Z","count":0,"uniques":0},{"timestamp":"2023-06-26T00:52:09.924Z","count":0,"uniques":0},{"timestamp":"2023-06-27T00:50:41.969Z","count":0,"uniques":0},{"timestamp":"2023-06-28T00:52:16.441Z","count":0,"uniques":0},{"timestamp":"2023-06-29T00:48:45.805Z","count":0,"uniques":0},{"timestamp":"2023-06-30T00:47:10.789Z","count":0,"uniques":0},{"timestamp":"2023-07-01T00:55:05.824Z","count":0,"uniques":0},{"timestamp":"2023-07-02T00:53:17.504Z","count":0,"uniques":0},{"timestamp":"2023-07-03T00:51:17.667Z","count":0,"uniques":0},{"timestamp":"2023-07-04T00:51:05.458Z","count":0,"uniques":0},{"timestamp":"2023-07-05T00:51:51.800Z","count":0,"uniques":0},{"timestamp":"2023-07-06T00:52:56.075Z","count":0,"uniques":0},{"timestamp":"2023-07-07T00:52:48.387Z","count":0,"uniques":0},{"timestamp":"2023-07-08T00:50:20.319Z","count":0,"uniques":0},{"timestamp":"2023-07-09T00:54:52.080Z","count":0,"uniques":0},{"timestamp":"2023-07-10T00:50:49.812Z","count":0,"uniques":0},{"timestamp":"2023-07-11T00:44:33.021Z","count":0,"uniques":0},{"timestamp":"2023-07-12T00:51:41.578Z","count":0,"uniques":0},{"timestamp":"2023-07-13T00:52:06.728Z","count":0,"uniques":0},{"timestamp":"2023-07-14T00:51:21.726Z","count":0,"uniques":0},{"timestamp":"2023-07-15T00:48:47.717Z","count":0,"uniques":0},{"timestamp":"2023-07-16T00:56:24.524Z","count":0,"uniques":0},{"timestamp":"2023-07-17T00:53:47.843Z","count":0,"uniques":0},{"timestamp":"2023-07-18T01:08:31.845Z","count":0,"uniques":0},{"timestamp":"2023-07-19T01:18:09.339Z","count":0,"uniques":0},{"timestamp":"2023-07-20T00:44:07.621Z","count":0,"uniques":0},{"timestamp":"2023-07-21T00:43:10.684Z","count":0,"uniques":0},{"timestamp":"2023-07-22T00:43:57.365Z","count":0,"uniques":0},{"timestamp":"2023-07-23T00:47:44.946Z","count":0,"uniques":0},{"timestamp":"2023-07-24T00:44:24.206Z","count":0,"uniques":0},{"timestamp":"2023-07-25T00:46:38.188Z","count":0,"uniques":0},{"timestamp":"2023-07-26T00:42:53.855Z","count":0,"uniques":0},{"timestamp":"2023-07-27T00:39:59.075Z","count":0,"uniques":0},{"timestamp":"2023-07-28T00:39:57.247Z","count":0,"uniques":0},{"timestamp":"2023-07-29T00:40:55.602Z","count":0,"uniques":0},{"timestamp":"2023-07-30T00:43:53.272Z","count":0,"uniques":0},{"timestamp":"2023-07-31T00:44:36.617Z","count":0,"uniques":0},{"timestamp":"2023-08-01T00:47:19.993Z","count":0,"uniques":0},{"timestamp":"2023-08-02T00:41:29.771Z","count":0,"uniques":0},{"timestamp":"2023-08-03T00:42:26.992Z","count":0,"uniques":0},{"timestamp":"2023-08-04T00:42:13.362Z","count":0,"uniques":0},{"timestamp":"2023-08-05T00:40:50.106Z","count":0,"uniques":0},{"timestamp":"2023-08-06T00:37:59.350Z","count":0,"uniques":0},{"timestamp":"2023-08-07T00:42:08.820Z","count":0,"uniques":0},{"timestamp":"2023-08-08T00:41:14.519Z","count":0,"uniques":0},{"timestamp":"2023-08-09T00:42:03.733Z","count":0,"uniques":0},{"timestamp":"2023-08-10T00:43:35.749Z","count":0,"uniques":0},{"timestamp":"2023-08-11T00:33:00.912Z","count":0,"uniques":0},{"timestamp":"2023-08-12T00:32:20.398Z","count":0,"uniques":0},{"timestamp":"2023-08-13T00:35:20.717Z","count":0,"uniques":0},{"timestamp":"2023-08-14T00:34:28.303Z","count":0,"uniques":0},{"timestamp":"2023-08-15T00:33:36.892Z","count":0,"uniques":0},{"timestamp":"2023-08-16T00:33:29.094Z","count":0,"uniques":0},{"timestamp":"2023-08-17T00:32:59.164Z","count":0,"uniques":0},{"timestamp":"2023-08-18T00:33:15.678Z","count":0,"uniques":0},{"timestamp":"2023-08-19T00:32:07.419Z","count":0,"uniques":0},{"timestamp":"2023-08-20T00:35:37.660Z","count":0,"uniques":0},{"timestamp":"2023-08-21T00:34:07.749Z","count":0,"uniques":0},{"timestamp":"2023-08-22T00:33:51.944Z","count":0,"uniques":0},{"timestamp":"2023-08-23T00:33:51.256Z","count":0,"uniques":0},{"timestamp":"2023-08-24T00:33:55.039Z","count":0,"uniques":0},{"timestamp":"2023-08-25T00:34:11.762Z","count":0,"uniques":0},{"timestamp":"2023-08-26T00:32:59.655Z","count":0,"uniques":0},{"timestamp":"2023-08-27T00:36:32.600Z","count":0,"uniques":0},{"timestamp":"2023-08-28T00:35:04.479Z","count":0,"uniques":0},{"timestamp":"2023-08-29T00:34:44.635Z","count":0,"uniques":0},{"timestamp":"2023-08-30T00:34:42.959Z","count":0,"uniques":0},{"timestamp":"2023-08-31T00:34:45.540Z","count":0,"uniques":0},{"timestamp":"2023-09-01T00:37:16.918Z","count":0,"uniques":0},{"timestamp":"2023-09-02T00:33:01.517Z","count":0,"uniques":0},{"timestamp":"2023-09-03T00:36:20.856Z","count":0,"uniques":0},{"timestamp":"2023-09-04T00:35:08.111Z","count":0,"uniques":0},{"timestamp":"2023-09-05T00:33:51.030Z","count":0,"uniques":0},{"timestamp":"2023-09-06T00:34:38.591Z","count":0,"uniques":0},{"timestamp":"2023-09-07T00:33:57.145Z","count":0,"uniques":0},{"timestamp":"2023-09-08T00:34:11.499Z","count":0,"uniques":0},{"timestamp":"2023-09-09T00:33:35.818Z","count":0,"uniques":0},{"timestamp":"2023-09-10T00:36:56.625Z","count":0,"uniques":0},{"timestamp":"2023-09-11T00:35:03.009Z","count":0,"uniques":0},{"timestamp":"2023-09-12T00:33:32.074Z","count":0,"uniques":0},{"timestamp":"2023-09-13T00:34:49.501Z","count":0,"uniques":0},{"timestamp":"2023-09-14T00:34:59.068Z","count":0,"uniques":0},{"timestamp":"2023-09-15T00:35:07.381Z","count":0,"uniques":0},{"timestamp":"2023-09-16T00:34:06.072Z","count":0,"uniques":0},{"timestamp":"2023-09-17T00:37:24.772Z","count":0,"uniques":0},{"timestamp":"2023-09-18T00:35:21.658Z","count":0,"uniques":0},{"timestamp":"2023-09-19T00:35:24.659Z","count":0,"uniques":0},{"timestamp":"2023-09-20T00:35:14.394Z","count":0,"uniques":0},{"timestamp":"2023-09-21T00:34:57.286Z","count":0,"uniques":0},{"timestamp":"2023-09-22T00:35:20.833Z","count":0,"uniques":0},{"timestamp":"2023-09-23T00:33:39.392Z","count":0,"uniques":0},{"timestamp":"2023-09-24T00:37:26.043Z","count":0,"uniques":0},{"timestamp":"2023-09-25T00:35:35.774Z","count":0,"uniques":0},{"timestamp":"2023-09-26T00:35:52.033Z","count":0,"uniques":0},{"timestamp":"2023-09-27T00:35:35.283Z","count":0,"uniques":0},{"timestamp":"2023-09-28T00:35:07.013Z","count":0,"uniques":0},{"timestamp":"2023-09-29T00:35:11.188Z","count":0,"uniques":0},{"timestamp":"2023-09-30T00:34:14.013Z","count":0,"uniques":0},{"timestamp":"2023-10-01T00:40:37.157Z","count":0,"uniques":0},{"timestamp":"2023-10-02T00:35:49.612Z","count":0,"uniques":0},{"timestamp":"2023-10-03T00:35:34.072Z","count":0,"uniques":0},{"timestamp":"2023-10-04T00:36:03.351Z","count":0,"uniques":0},{"timestamp":"2023-10-05T00:35:15.859Z","count":0,"uniques":0},{"timestamp":"2023-10-06T00:35:26.722Z","count":0,"uniques":0},{"timestamp":"2023-10-07T00:34:45.447Z","count":0,"uniques":0},{"timestamp":"2023-10-08T00:38:25.020Z","count":0,"uniques":0},{"timestamp":"2023-10-09T00:35:54.732Z","count":0,"uniques":0},{"timestamp":"2023-10-10T00:35:10.509Z","count":0,"uniques":0},{"timestamp":"2023-10-11T00:35:09.140Z","count":0,"uniques":0},{"timestamp":"2023-10-12T00:33:29.535Z","count":0,"uniques":0},{"timestamp":"2023-10-13T00:36:34.115Z","count":0,"uniques":0},{"timestamp":"2023-10-14T00:34:17.389Z","count":0,"uniques":0},{"timestamp":"2023-10-15T00:38:21.093Z","count":0,"uniques":0},{"timestamp":"2023-10-16T00:36:26.666Z","count":0,"uniques":0},{"timestamp":"2023-10-17T00:35:52.006Z","count":0,"uniques":0},{"timestamp":"2023-10-18T00:35:56.188Z","count":0,"uniques":0},{"timestamp":"2023-10-19T00:35:26.990Z","count":0,"uniques":0},{"timestamp":"2023-10-20T00:35:30.408Z","count":0,"uniques":0},{"timestamp":"2023-10-21T00:34:22.667Z","count":0,"uniques":0},{"timestamp":"2023-10-22T00:38:11.929Z","count":0,"uniques":0},{"timestamp":"2023-10-23T00:35:46.343Z","count":0,"uniques":0},{"timestamp":"2023-10-24T00:35:29.027Z","count":0,"uniques":0},{"timestamp":"2023-10-25T00:35:15.902Z","count":0,"uniques":0},{"timestamp":"2023-10-26T00:34:51.540Z","count":0,"uniques":0},{"timestamp":"2023-10-27T00:34:47.428Z","count":0,"uniques":0},{"timestamp":"2023-10-28T00:34:10.645Z","count":0,"uniques":0},{"timestamp":"2023-10-29T00:37:47.709Z","count":0,"uniques":0},{"timestamp":"2023-10-30T00:36:10.103Z","count":0,"uniques":0},{"timestamp":"2023-10-31T00:36:08.126Z","count":0,"uniques":0},{"timestamp":"2023-11-01T00:38:02.948Z","count":0,"uniques":0},{"timestamp":"2023-11-02T00:35:35.245Z","count":0,"uniques":0},{"timestamp":"2023-11-03T00:35:35.932Z","count":0,"uniques":0},{"timestamp":"2023-11-04T00:35:13.270Z","count":0,"uniques":0},{"timestamp":"2023-11-05T00:38:34.470Z","count":0,"uniques":0},{"timestamp":"2023-11-06T00:36:50.622Z","count":0,"uniques":0},{"timestamp":"2023-11-07T00:36:31.995Z","count":0,"uniques":0},{"timestamp":"2023-11-08T00:35:59.515Z","count":0,"uniques":0},{"timestamp":"2023-11-09T00:35:48.281Z","count":0,"uniques":0},{"timestamp":"2023-11-10T00:36:24.313Z","count":0,"uniques":0},{"timestamp":"2023-11-11T00:35:39.427Z","count":0,"uniques":0},{"timestamp":"2023-11-12T00:38:52.064Z","count":0,"uniques":0},{"timestamp":"2023-11-13T00:37:19.262Z","count":0,"uniques":0},{"timestamp":"2023-11-14T00:36:14.855Z","count":0,"uniques":0},{"timestamp":"2023-11-15T00:36:52.107Z","count":0,"uniques":0},{"timestamp":"2023-11-16T00:37:30.191Z","count":0,"uniques":0},{"timestamp":"2023-11-17T00:37:18.712Z","count":0,"uniques":0},{"timestamp":"2023-11-18T00:36:30.359Z","count":0,"uniques":0},{"timestamp":"2023-11-19T00:40:11.099Z","count":0,"uniques":0},{"timestamp":"2023-11-20T00:38:03.424Z","count":0,"uniques":0},{"timestamp":"2023-11-21T00:38:03.234Z","count":0,"uniques":0},{"timestamp":"2023-11-22T00:39:08.151Z","count":0,"uniques":0},{"timestamp":"2023-11-23T00:37:23.914Z","count":0,"uniques":0},{"timestamp":"2023-11-24T00:36:15.663Z","count":0,"uniques":0},{"timestamp":"2023-11-25T00:35:34.116Z","count":0,"uniques":0},{"timestamp":"2023-11-26T00:39:44.154Z","count":0,"uniques":0},{"timestamp":"2023-11-27T00:37:43.564Z","count":0,"uniques":0},{"timestamp":"2023-11-28T00:37:59.023Z","count":0,"uniques":0},{"timestamp":"2023-11-29T00:37:54.865Z","count":0,"uniques":0},{"timestamp":"2023-11-30T00:37:34.891Z","count":0,"uniques":0},{"timestamp":"2023-12-01T00:40:59.794Z","count":0,"uniques":0},{"timestamp":"2023-12-02T00:36:26.892Z","count":0,"uniques":0},{"timestamp":"2023-12-03T00:39:51.277Z","count":0,"uniques":0},{"timestamp":"2023-12-04T00:38:14.867Z","count":0,"uniques":0},{"timestamp":"2023-12-05T00:38:09.274Z","count":0,"uniques":0},{"timestamp":"2023-12-06T00:38:12.891Z","count":0,"uniques":0},{"timestamp":"2023-12-07T00:37:29.071Z","count":0,"uniques":0},{"timestamp":"2023-12-08T00:38:00.151Z","count":0,"uniques":0},{"timestamp":"2023-12-09T00:36:46.996Z","count":0,"uniques":0},{"timestamp":"2023-12-10T00:40:41.907Z","count":0,"uniques":0},{"timestamp":"2023-12-11T00:38:31.973Z","count":0,"uniques":0},{"timestamp":"2023-12-12T00:38:16.564Z","count":0,"uniques":0},{"timestamp":"2023-12-13T00:37:38.885Z","count":0,"uniques":0},{"timestamp":"2023-12-14T00:37:14.000Z","count":0,"uniques":0},{"timestamp":"2023-12-15T00:38:11.664Z","count":0,"uniques":0},{"timestamp":"2023-12-16T00:37:07.893Z","count":0,"uniques":0},{"timestamp":"2023-12-17T00:40:44.146Z","count":0,"uniques":0},{"timestamp":"2023-12-18T00:38:57.796Z","count":0,"uniques":0},{"timestamp":"2023-12-19T00:37:56.286Z","count":0,"uniques":0},{"timestamp":"2023-12-20T00:30:45.857Z","count":0,"uniques":0},{"timestamp":"2023-12-21T00:37:08.733Z","count":0,"uniques":0},{"timestamp":"2023-12-22T00:36:55.530Z","count":0,"uniques":0},{"timestamp":"2023-12-23T00:35:37.813Z","count":0,"uniques":0},{"timestamp":"2023-12-24T00:39:52.799Z","count":0,"uniques":0},{"timestamp":"2023-12-25T00:37:54.807Z","count":0,"uniques":0},{"timestamp":"2023-12-26T00:36:13.370Z","count":0,"uniques":0},{"timestamp":"2023-12-27T00:36:12.556Z","count":0,"uniques":0},{"timestamp":"2023-12-28T00:36:04.523Z","count":0,"uniques":0},{"timestamp":"2023-12-29T00:30:33.693Z","count":0,"uniques":0},{"timestamp":"2023-12-30T00:36:18.599Z","count":0,"uniques":0},{"timestamp":"2023-12-31T00:40:16.145Z","count":0,"uniques":0},{"timestamp":"2024-01-01T00:41:29.322Z","count":0,"uniques":0},{"timestamp":"2024-01-02T00:37:02.756Z","count":0,"uniques":0},{"timestamp":"2024-01-03T00:37:05.031Z","count":0,"uniques":0},{"timestamp":"2024-01-04T00:37:44.292Z","count":0,"uniques":0},{"timestamp":"2024-01-05T00:37:53.817Z","count":0,"uniques":0},{"timestamp":"2024-01-06T00:37:19.254Z","count":0,"uniques":0},{"timestamp":"2024-01-07T00:41:37.384Z","count":0,"uniques":0},{"timestamp":"2024-01-08T00:38:54.177Z","count":0,"uniques":0},{"timestamp":"2024-01-09T00:38:27.977Z","count":0,"uniques":0},{"timestamp":"2024-01-10T00:38:28.705Z","count":0,"uniques":0},{"timestamp":"2024-01-11T00:38:26.923Z","count":0,"uniques":0},{"timestamp":"2024-01-12T00:38:19.036Z","count":0,"uniques":0},{"timestamp":"2024-01-13T00:37:47.492Z","count":0,"uniques":0},{"timestamp":"2024-01-14T00:41:33.341Z","count":0,"uniques":0},{"timestamp":"2024-01-15T00:40:00.193Z","count":0,"uniques":0},{"timestamp":"2024-01-16T00:37:58.610Z","count":0,"uniques":0},{"timestamp":"2024-01-17T00:38:32.733Z","count":0,"uniques":0},{"timestamp":"2024-01-18T00:38:10.532Z","count":0,"uniques":0},{"timestamp":"2024-01-19T00:38:38.902Z","count":0,"uniques":0},{"timestamp":"2024-01-20T00:37:43.020Z","count":0,"uniques":0},{"timestamp":"2024-01-21T00:41:50.284Z","count":0,"uniques":0},{"timestamp":"2024-01-22T00:40:10.992Z","count":0,"uniques":0},{"timestamp":"2024-01-23T00:38:57.090Z","count":0,"uniques":0},{"timestamp":"2024-01-24T00:38:58.331Z","count":0,"uniques":0},{"timestamp":"2024-01-25T00:38:54.692Z","count":0,"uniques":0},{"timestamp":"2024-01-26T00:36:12.058Z","count":0,"uniques":0},{"timestamp":"2024-01-27T00:36:03.347Z","count":0,"uniques":0},{"timestamp":"2024-01-28T00:38:26.355Z","count":0,"uniques":0},{"timestamp":"2024-01-29T00:36:05.409Z","count":0,"uniques":0},{"timestamp":"2024-01-30T00:35:52.986Z","count":0,"uniques":0},{"timestamp":"2024-01-31T00:36:09.265Z","count":0,"uniques":0},{"timestamp":"2024-02-01T00:37:40.215Z","count":0,"uniques":0},{"timestamp":"2024-02-02T00:36:17.591Z","count":0,"uniques":0},{"timestamp":"2024-02-03T00:35:41.367Z","count":0,"uniques":0},{"timestamp":"2024-02-04T00:38:48.646Z","count":0,"uniques":0},{"timestamp":"2024-02-05T00:36:56.529Z","count":0,"uniques":0},{"timestamp":"2024-02-06T00:35:22.681Z","count":0,"uniques":0},{"timestamp":"2024-02-07T00:34:07.833Z","count":0,"uniques":0},{"timestamp":"2024-02-08T00:35:22.087Z","count":0,"uniques":0},{"timestamp":"2024-02-09T00:35:02.075Z","count":0,"uniques":0},{"timestamp":"2024-02-10T00:34:31.000Z","count":0,"uniques":0},{"timestamp":"2024-02-11T00:39:02.128Z","count":0,"uniques":0},{"timestamp":"2024-02-12T00:36:22.787Z","count":0,"uniques":0},{"timestamp":"2024-02-13T00:36:15.804Z","count":0,"uniques":0},{"timestamp":"2024-02-14T00:35:54.092Z","count":0,"uniques":0},{"timestamp":"2024-02-15T00:36:03.076Z","count":0,"uniques":0},{"timestamp":"2024-02-16T00:35:16.778Z","count":0,"uniques":0},{"timestamp":"2024-02-17T00:35:17.111Z","count":0,"uniques":0},{"timestamp":"2024-02-18T00:38:17.223Z","count":0,"uniques":0},{"timestamp":"2024-02-19T00:36:58.740Z","count":0,"uniques":0},{"timestamp":"2024-02-20T00:35:13.319Z","count":0,"uniques":0},{"timestamp":"2024-02-21T00:35:52.948Z","count":0,"uniques":0},{"timestamp":"2024-02-22T00:35:31.752Z","count":0,"uniques":0},{"timestamp":"2024-02-23T00:35:14.351Z","count":0,"uniques":0},{"timestamp":"2024-02-24T00:33:43.376Z","count":0,"uniques":0},{"timestamp":"2024-02-25T00:38:44.269Z","count":0,"uniques":0},{"timestamp":"2024-02-26T00:37:13.532Z","count":0,"uniques":0},{"timestamp":"2024-02-27T00:35:28.371Z","count":0,"uniques":0},{"timestamp":"2024-02-28T00:34:45.424Z","count":0,"uniques":0},{"timestamp":"2024-02-29T00:35:32.080Z","count":0,"uniques":0},{"timestamp":"2024-03-01T00:39:46.317Z","count":0,"uniques":0},{"timestamp":"2024-03-02T00:34:40.660Z","count":0,"uniques":0},{"timestamp":"2024-03-03T00:37:51.966Z","count":0,"uniques":0},{"timestamp":"2024-03-04T00:36:29.231Z","count":0,"uniques":0},{"timestamp":"2024-03-05T00:35:31.322Z","count":0,"uniques":0},{"timestamp":"2024-03-06T00:35:53.384Z","count":0,"uniques":0},{"timestamp":"2024-03-07T00:29:09.953Z","count":0,"uniques":0},{"timestamp":"2024-03-08T00:35:49.911Z","count":0,"uniques":0},{"timestamp":"2024-03-09T00:34:27.355Z","count":0,"uniques":0},{"timestamp":"2024-03-10T00:38:46.474Z","count":0,"uniques":0},{"timestamp":"2024-03-11T00:37:00.874Z","count":0,"uniques":0},{"timestamp":"2024-03-12T00:35:16.718Z","count":0,"uniques":0},{"timestamp":"2024-03-13T00:36:04.209Z","count":0,"uniques":0},{"timestamp":"2024-03-14T00:35:15.664Z","count":0,"uniques":0}]
